resumer/__init__.py
resumer/cli.py
resumer/base/check_func.py
resumer/base/match.py
resumer/core/data.py
resumer/core/engine.py
resumer/core/filter.py
resumer/engines/__init__.py
resumer/engines/generic.py
resumer/engines/tex.py
resumer/preset/awesome.tex
resumer/utils/__init__.py
resumer/utils/download.py
resumer/utils/string.py
resumer-1.0.2.dist-info/LICENSE
resumer-1.0.2.dist-info/METADATA
resumer-1.0.2.dist-info/WHEEL
resumer-1.0.2.dist-info/entry_points.txt
resumer-1.0.2.dist-info/top_level.txt
resumer-1.0.2.dist-info/RECORD
