Metadata-Version: 2.1
Name: resumer
Version: 1.0.2
Summary: pandoc based generator with advanced filter support
Home-page: https://github.com/zackaryw/resumer
Author: Zackary W
License: MIT
Classifier: Programming Language :: Python :: 3.11
License-File: LICENSE
Requires-Dist: pydantic
Requires-Dist: click
Requires-Dist: requests
